[{"node_0": {"label_name": "Object", "node_information": {"name": "Carving_Word5", "timestamp": "20230829142040", "flame": "007908", "event": "HoverEnter", "by": "RHand(Direct)", "username": "nishi"}}}, {"node_1": {"label_name": "Object", "node_information": {"name": "Carving_Word5", "timestamp": "20230829142045", "flame": "008199", "event": "SelectExit", "by": "RHand(Direct)", "username": "nishi"}}}, {"node_2": {"label_name": "Object", "node_information": {"name": "Carving_Word5", "timestamp": "20230829142045", "flame": "008223", "event": "HoverExit", "by": "RHand(Direct)", "username": "nishi"}}}, {"node_4": {"label_name": "Object", "node_information": {"name": "Carving_Word5", "timestamp": "20230829142052", "flame": "008699", "event": "HoverEnter", "by": "RHand(Direct)", "username": "nishi"}}}, {"node_5": {"label_name": "Object", "node_information": {"name": "Carving_Word5", "timestamp": "20230829142053", "flame": "008825", "event": "SelectExit", "by": "RHand(Direct)", "username": "nishi"}}}, {"node_6": {"label_name": "Object", "node_information": {"name": "Carving_Word5", "timestamp": "20230829142054", "flame": "008847", "event": "HoverExit", "by": "RHand(Direct)", "username": "nishi"}}}, {"node_8": {"label_name": "Object", "node_information": {"name": "Carving_Word5", "timestamp": "20230829142100", "flame": "009343", "event": "HoverEnter", "by": "RHand(Direct)", "username": "nishi"}}}, {"node_9": {"label_name": "Object", "node_information": {"name": "Carving_Word5", "timestamp": "20230829142103", "flame": "009540", "event": "SelectExit", "by": "RHand(Direct)", "username": "nishi"}}}, {"node_10": {"label_name": "Object", "node_information": {"name": "Carving_Word5", "timestamp": "20230829142104", "flame": "009564", "event": "HoverExit", "by": "RHand(Direct)", "username": "nishi"}}}, {"node_12": {"label_name": "Object", "node_information": {"name": "Carving_Word5", "timestamp": "20230829142113", "flame": "010258", "event": "HoverEnter", "by": "RHand(Direct)", "username": "nishi"}}}, {"node_13": {"label_name": "Object", "node_information": {"name": "Carving_Word5", "timestamp": "20230829142115", "flame": "010411", "event": "SelectExit", "by": "RHand(Direct)", "username": "nishi"}}}, {"node_14": {"label_name": "Object", "node_information": {"name": "Carving_Word5", "timestamp": "20230829142116", "flame": "010452", "event": "HoverExit", "by": "RHand(Direct)", "username": "nishi"}}}, {"node_16": {"label_name": "Object", "node_information": {"name": "Carving_Word5", "timestamp": "20230829142121", "flame": "010818", "event": "HoverEnter", "by": "LHand(DIrect)", "username": "nishi"}}}, {"node_17": {"label_name": "Object", "node_information": {"name": "Carving_Word5", "timestamp": "20230829142123", "flame": "010973", "event": "SelectExit", "by": "LHand(DIrect)", "username": "nishi"}}}, {"node_18": {"label_name": "Object", "node_information": {"name": "Carving_Word5", "timestamp": "20230829142123", "flame": "010995", "event": "HoverExit", "by": "LHand(DIrect)", "username": "nishi"}}}, {"node_20": {"label_name": "Object", "node_information": {"name": "Carving_Word5", "timestamp": "20230829142130", "flame": "011490", "event": "HoverEnter", "by": "RHand(Direct)", "username": "nishi"}}}, {"node_21": {"label_name": "Object", "node_information": {"name": "Carving_Word5", "timestamp": "20230829142132", "flame": "011612", "event": "SelectExit", "by": "RHand(Direct)", "username": "nishi"}}}, {"node_22": {"label_name": "Object", "node_information": {"name": "Carving_Word5", "timestamp": "20230829142134", "flame": "011735", "event": "SelectExit", "by": "RHand(Direct)", "username": "nishi"}}}, {"node_23": {"label_name": "Object", "node_information": {"name": "Carving_Word5", "timestamp": "20230829142134", "flame": "011754", "event": "HoverExit", "by": "RHand(Direct)", "username": "nishi"}}}, {"node_24": {"label_name": "Object", "node_information": {"name": "Vintage_Word8", "timestamp": "20230829142140", "flame": "012155", "event": "HoverEnter", "by": "RHand(Direct)", "username": "nishi"}}}, {"node_26": {"label_name": "Object", "node_information": {"name": "Vintage_Word8", "timestamp": "20230829142142", "flame": "012356", "event": "HoverEnter", "by": "RHand(Direct)", "username": "nishi"}}}, {"node_27": {"label_name": "Object", "node_information": {"name": "Vintage_Word8", "timestamp": "20230829142142", "flame": "012356", "event": "SelectEnter", "by": "RHand(Direct)", "username": "nishi"}}}, {"node_32": {"label_name": "Object", "node_information": {"name": "Vintage_Word8", "timestamp": "20230829142151", "flame": "012944", "event": "SelectExit", "by": "RHand(Direct)", "username": "nishi"}}}, {"node_33": {"label_name": "Object", "node_information": {"name": "Vintage_Word8", "timestamp": "20230829142151", "flame": "012944", "event": "HoverExit", "by": "RHand(Direct)", "username": "nishi"}}}, {"node_36": {"label_name": "Object", "node_information": {"name": "Vintage_Word8", "timestamp": "20230829142151", "flame": "012981", "event": "HoverEnter", "by": "RHand(Direct)", "username": "nishi"}}}, {"node_37": {"label_name": "Object", "node_information": {"name": "Vintage_Word8", "timestamp": "20230829142151", "flame": "012981", "event": "SelectEnter", "by": "RHand(Direct)", "username": "nishi"}}}, {"node_38": {"label_name": "Object", "node_information": {"name": "Vintage_Word8", "timestamp": "20230829142157", "flame": "013431", "event": "HoverEnter", "by": "LHand(DIrect)", "username": "nishi"}}}, {"node_44": {"label_name": "Object", "node_information": {"name": "Vintage_Word8", "timestamp": "20230829142205", "flame": "013980", "event": "SelectExit", "by": "RHand(Direct)", "username": "nishi"}}}, {"node_45": {"label_name": "Object", "node_information": {"name": "Vintage_Word8", "timestamp": "20230829142205", "flame": "013980", "event": "HoverExit", "by": "RHand(Direct)", "username": "nishi"}}}, {"node_48": {"label_name": "Object", "node_information": {"name": "Vintage_Word8", "timestamp": "20230829142205", "flame": "014009", "event": "HoverEnter", "by": "RHand(Direct)", "username": "nishi"}}}, {"node_49": {"label_name": "Object", "node_information": {"name": "Vintage_Word8", "timestamp": "20230829142205", "flame": "014009", "event": "SelectEnter", "by": "RHand(Direct)", "username": "nishi"}}}, {"node_50": {"label_name": "Object", "node_information": {"name": "Vintage_Word8", "timestamp": "20230829142211", "flame": "014405", "event": "HoverEnter", "by": "RHand(Direct)", "username": "nishi"}}}, {"node_56": {"label_name": "Object", "node_information": {"name": "Vintage_Word8", "timestamp": "20230829142217", "flame": "014873", "event": "SelectExit", "by": "RHand(Direct)", "username": "nishi"}}}, {"node_57": {"label_name": "Object", "node_information": {"name": "Vintage_Word8", "timestamp": "20230829142217", "flame": "014873", "event": "HoverExit", "by": "RHand(Direct)", "username": "nishi"}}}, {"node_60": {"label_name": "Object", "node_information": {"name": "Vintage_Word8", "timestamp": "20230829142218", "flame": "014934", "event": "HoverEnter", "by": "RHand(Direct)", "username": "nishi"}}}, {"node_61": {"label_name": "Object", "node_information": {"name": "Vintage_Word8", "timestamp": "20230829142218", "flame": "014934", "event": "SelectEnter", "by": "RHand(Direct)", "username": "nishi"}}}, {"node_67": {"label_name": "Object", "node_information": {"name": "Vintage_Word8", "timestamp": "20230829142232", "flame": "015934", "event": "SelectExit", "by": "RHand(Direct)", "username": "nishi"}}}, {"node_68": {"label_name": "Object", "node_information": {"name": "Vintage_Word8", "timestamp": "20230829142232", "flame": "015934", "event": "HoverExit", "by": "RHand(Direct)", "username": "nishi"}}}, {"node_71": {"label_name": "Object", "node_information": {"name": "Dandelion_Word9", "timestamp": "20230829142233", "flame": "015985", "event": "HoverEnter", "by": "RHand(Direct)", "username": "nishi"}}}, {"node_72": {"label_name": "Object", "node_information": {"name": "Dandelion_Word9", "timestamp": "20230829142233", "flame": "015985", "event": "SelectEnter", "by": "RHand(Direct)", "username": "nishi"}}}, {"node_73": {"label_name": "Object", "node_information": {"name": "Dandelion_Word9", "timestamp": "20230829142242", "flame": "016689", "event": "HoverEnter", "by": "RHand(Direct)", "username": "nishi"}}}, {"node_75": {"label_name": "Object", "node_information": {"name": "Dandelion_Word9", "timestamp": "20230829142246", "flame": "016955", "event": "HoverEnter", "by": "RHand(Direct)", "username": "nishi"}}}, {"node_76": {"label_name": "Object", "node_information": {"name": "Dandelion_Word9", "timestamp": "20230829142246", "flame": "016955", "event": "SelectEnter", "by": "RHand(Direct)", "username": "nishi"}}}, {"node_77": {"label_name": "Object", "node_information": {"name": "Dandelion_Word9", "timestamp": "20230829142258", "flame": "017826", "event": "HoverEnter", "by": "RHand(Direct)", "username": "nishi"}}}, {"node_79": {"label_name": "Object", "node_information": {"name": "Dandelion_Word9", "timestamp": "20230829142302", "flame": "018112", "event": "HoverEnter", "by": "RHand(Direct)", "username": "nishi"}}}, {"node_80": {"label_name": "Object", "node_information": {"name": "Dandelion_Word9", "timestamp": "20230829142302", "flame": "018112", "event": "SelectEnter", "by": "RHand(Direct)", "username": "nishi"}}}, {"node_81": {"label_name": "Object", "node_information": {"name": "Dandelion_Word9", "timestamp": "20230829142308", "flame": "018511", "event": "HoverEnter", "by": "RHand(Direct)", "username": "nishi"}}}, {"node_83": {"label_name": "Object", "node_information": {"name": "Dandelion_Word9", "timestamp": "20230829142311", "flame": "018734", "event": "HoverEnter", "by": "RHand(Direct)", "username": "nishi"}}}, {"node_84": {"label_name": "Object", "node_information": {"name": "Dandelion_Word9", "timestamp": "20230829142311", "flame": "018734", "event": "SelectEnter", "by": "RHand(Direct)", "username": "nishi"}}}, {"node_85": {"label_name": "Object", "node_information": {"name": "Dandelion_Word9", "timestamp": "20230829142315", "flame": "019053", "event": "HoverEnter", "by": "RHand(Direct)", "username": "nishi"}}}, {"node_86": {"label_name": "Object", "node_information": {"name": "Dandelion_Word9", "timestamp": "20230829142317", "flame": "019213", "event": "SelectExit", "by": "RHand(Direct)", "username": "nishi"}}}, {"node_88": {"label_name": "Object", "node_information": {"name": "Dandelion_Word9", "timestamp": "20230829142323", "flame": "019606", "event": "HoverEnter", "by": "RHand(Direct)", "username": "nishi"}}}, {"node_89": {"label_name": "Object", "node_information": {"name": "Dandelion_Word9", "timestamp": "20230829142323", "flame": "019606", "event": "SelectEnter", "by": "RHand(Direct)", "username": "nishi"}}}, {"node_90": {"label_name": "Object", "node_information": {"name": "Dandelion_Word9", "timestamp": "20230829142327", "flame": "019904", "event": "HoverEnter", "by": "RHand(Direct)", "username": "nishi"}}}, {"node_92": {"label_name": "Object", "node_information": {"name": "Dandelion_Word9", "timestamp": "20230829142330", "flame": "020130", "event": "HoverEnter", "by": "RHand(Direct)", "username": "nishi"}}}, {"node_93": {"label_name": "Object", "node_information": {"name": "Dandelion_Word9", "timestamp": "20230829142330", "flame": "020130", "event": "SelectEnter", "by": "RHand(Direct)", "username": "nishi"}}}, {"node_94": {"label_name": "Object", "node_information": {"name": "Chick_Word3", "timestamp": "20230829142350", "flame": "021521", "event": "HoverEnter", "by": "RHand(Direct)", "username": "nishi"}}}, {"node_95": {"label_name": "Object", "node_information": {"name": "Chick_Word3", "timestamp": "20230829142351", "flame": "021619", "event": "HoverExit", "by": "RHand(Direct)", "username": "nishi"}}}, {"node_96": {"label_name": "Object", "node_information": {"name": "Acorn_Word1", "timestamp": "20230829142355", "flame": "021887", "event": "HoverEnter", "by": "RHand(Direct)", "username": "nishi"}}}, {"node_97": {"label_name": "Object", "node_information": {"name": "Acorn_Word1", "timestamp": "20230829142400", "flame": "022273", "event": "SelectExit", "by": "RHand(Direct)", "username": "nishi"}}}, {"node_98": {"label_name": "Object", "node_information": {"name": "Ewe_Word2", "timestamp": "20230829142400", "flame": "022273", "event": "HoverEnter", "by": "RHand(Direct)", "username": "nishi"}}}, {"node_99": {"label_name": "Object", "node_information": {"name": "Acorn_Word1", "timestamp": "20230829142400", "flame": "022285", "event": "HoverExit", "by": "RHand(Direct)", "username": "nishi"}}}, {"node_101": {"label_name": "Object", "node_information": {"name": "Ewe_Word2", "timestamp": "20230829142401", "flame": "022324", "event": "HoverExit", "by": "RHand(Direct)", "username": "nishi"}}}, {"node_102": {"label_name": "Object", "node_information": {"name": "Ewe_Word2", "timestamp": "20230829142401", "flame": "022338", "event": "HoverEnter", "by": "RHand(Direct)", "username": "nishi"}}}, {"node_103": {"label_name": "Object", "node_information": {"name": "Acorn_Word1", "timestamp": "20230829142401", "flame": "022350", "event": "HoverEnter", "by": "RHand(Direct)", "username": "nishi"}}}, {"node_104": {"label_name": "Object", "node_information": {"name": "Ewe_Word2", "timestamp": "20230829142402", "flame": "022384", "event": "HoverExit", "by": "RHand(Direct)", "username": "nishi"}}}, {"node_105": {"label_name": "Object", "node_information": {"name": "Acorn_Word1", "timestamp": "20230829142403", "flame": "022491", "event": "SelectExit", "by": "RHand(Direct)", "username": "nishi"}}}, {"node_106": {"label_name": "Object", "node_information": {"name": "Ewe_Word2", "timestamp": "20230829142403", "flame": "022491", "event": "HoverEnter", "by": "RHand(Direct)", "username": "nishi"}}}, {"node_108": {"label_name": "Object", "node_information": {"name": "Acorn_Word1", "timestamp": "20230829142403", "flame": "022505", "event": "HoverExit", "by": "RHand(Direct)", "username": "nishi"}}}, {"node_109": {"label_name": "Object", "node_information": {"name": "Acorn_Word1", "timestamp": "20230829142404", "flame": "022554", "event": "HoverEnter", "by": "RHand(Direct)", "username": "nishi"}}}, {"node_110": {"label_name": "Object", "node_information": {"name": "Ewe_Word2", "timestamp": "20230829142405", "flame": "022582", "event": "HoverExit", "by": "RHand(Direct)", "username": "nishi"}}}, {"node_111": {"label_name": "Object", "node_information": {"name": "Acorn_Word1", "timestamp": "20230829142408", "flame": "022846", "event": "SelectExit", "by": "RHand(Direct)", "username": "nishi"}}}, {"node_112": {"label_name": "Object", "node_information": {"name": "Ewe_Word2", "timestamp": "20230829142408", "flame": "022846", "event": "HoverEnter", "by": "RHand(Direct)", "username": "nishi"}}}, {"node_114": {"label_name": "Object", "node_information": {"name": "Acorn_Word1", "timestamp": "20230829142408", "flame": "022860", "event": "HoverExit", "by": "RHand(Direct)", "username": "nishi"}}}, {"node_115": {"label_name": "Object", "node_information": {"name": "Acorn_Word1", "timestamp": "20230829142409", "flame": "022899", "event": "HoverEnter", "by": "RHand(Direct)", "username": "nishi"}}}, {"node_116": {"label_name": "Object", "node_information": {"name": "Ewe_Word2", "timestamp": "20230829142410", "flame": "022945", "event": "HoverExit", "by": "RHand(Direct)", "username": "nishi"}}}, {"node_117": {"label_name": "Object", "node_information": {"name": "Acorn_Word1", "timestamp": "20230829142412", "flame": "023140", "event": "SelectExit", "by": "RHand(Direct)", "username": "nishi"}}}, {"node_119": {"label_name": "Object", "node_information": {"name": "Ewe_Word2", "timestamp": "20230829142412", "flame": "023144", "event": "HoverEnter", "by": "RHand(Direct)", "username": "nishi"}}}, {"node_120": {"label_name": "Object", "node_information": {"name": "Acorn_Word1", "timestamp": "20230829142413", "flame": "023158", "event": "HoverExit", "by": "RHand(Direct)", "username": "nishi"}}}, {"node_121": {"label_name": "Object", "node_information": {"name": "Ewe_Word2", "timestamp": "20230829142413", "flame": "023184", "event": "HoverExit", "by": "RHand(Direct)", "username": "nishi"}}}, {"node_122": {"label_name": "Object", "node_information": {"name": "Acorn_Word1", "timestamp": "20230829142413", "flame": "023191", "event": "HoverEnter", "by": "RHand(Direct)", "username": "nishi"}}}, {"node_123": {"label_name": "Object", "node_information": {"name": "Acorn_Word1", "timestamp": "20230829142420", "flame": "023666", "event": "SelectExit", "by": "RHand(Direct)", "username": "nishi"}}}, {"node_124": {"label_name": "Object", "node_information": {"name": "Chick_Word3", "timestamp": "20230829142420", "flame": "023666", "event": "HoverEnter", "by": "RHand(Direct)", "username": "nishi"}}}, {"node_125": {"label_name": "Object", "node_information": {"name": "Acorn_Word1", "timestamp": "20230829142420", "flame": "023683", "event": "HoverExit", "by": "RHand(Direct)", "username": "nishi"}}}, {"node_126": {"label_name": "Object", "node_information": {"name": "Chick_Word3", "timestamp": "20230829142420", "flame": "023717", "event": "HoverExit", "by": "RHand(Direct)", "username": "nishi"}}}, {"node_127": {"label_name": "Object", "node_information": {"name": "Acorn_Word1", "timestamp": "20230829142421", "flame": "023781", "event": "HoverEnter", "by": "RHand(Direct)", "username": "nishi"}}}, {"node_128": {"label_name": "Object", "node_information": {"name": "Acorn_Word1", "timestamp": "20230829142423", "flame": "023897", "event": "SelectExit", "by": "RHand(Direct)", "username": "nishi"}}}, {"node_129": {"label_name": "Object", "node_information": {"name": "Chick_Word3", "timestamp": "20230829142423", "flame": "023897", "event": "HoverEnter", "by": "RHand(Direct)", "username": "nishi"}}}, {"node_130": {"label_name": "Object", "node_information": {"name": "Acorn_Word1", "timestamp": "20230829142423", "flame": "023914", "event": "HoverExit", "by": "RHand(Direct)", "username": "nishi"}}}, {"node_131": {"label_name": "Object", "node_information": {"name": "Chick_Word3", "timestamp": "20230829142423", "flame": "023922", "event": "HoverExit", "by": "RHand(Direct)", "username": "nishi"}}}, {"node_132": {"label_name": "Object", "node_information": {"name": "Acorn_Word1", "timestamp": "20230829142423", "flame": "023927", "event": "HoverEnter", "by": "RHand(Direct)", "username": "nishi"}}}, {"node_133": {"label_name": "Object", "node_information": {"name": "Acorn_Word1", "timestamp": "20230829142425", "flame": "024053", "event": "SelectExit", "by": "RHand(Direct)", "username": "nishi"}}}, {"node_134": {"label_name": "Object", "node_information": {"name": "Chick_Word3", "timestamp": "20230829142425", "flame": "024053", "event": "HoverEnter", "by": "RHand(Direct)", "username": "nishi"}}}, {"node_135": {"label_name": "Object", "node_information": {"name": "Acorn_Word1", "timestamp": "20230829142426", "flame": "024110", "event": "HoverExit", "by": "RHand(Direct)", "username": "nishi"}}}, {"node_136": {"label_name": "Object", "node_information": {"name": "Chick_Word3", "timestamp": "20230829142426", "flame": "024114", "event": "HoverExit", "by": "RHand(Direct)", "username": "nishi"}}}, {"node_137": {"label_name": "Object", "node_information": {"name": "Acorn_Word1", "timestamp": "20230829142429", "flame": "024334", "event": "HoverEnter", "by": "RHand(Direct)", "username": "nishi"}}}, {"node_138": {"label_name": "Object", "node_information": {"name": "Chick_Word3", "timestamp": "20230829142429", "flame": "024336", "event": "HoverEnter", "by": "RHand(Direct)", "username": "nishi"}}}, {"node_139": {"label_name": "Object", "node_information": {"name": "Chick_Word3", "timestamp": "20230829142429", "flame": "024377", "event": "HoverExit", "by": "RHand(Direct)", "username": "nishi"}}}, {"node_140": {"label_name": "Object", "node_information": {"name": "Acorn_Word1", "timestamp": "20230829142434", "flame": "024683", "event": "SelectExit", "by": "RHand(Direct)", "username": "nishi"}}}, {"node_141": {"label_name": "Object", "node_information": {"name": "Ewe_Word2", "timestamp": "20230829142434", "flame": "024683", "event": "HoverEnter", "by": "RHand(Direct)", "username": "nishi"}}}, {"node_143": {"label_name": "Object", "node_information": {"name": "Acorn_Word1", "timestamp": "20230829142434", "flame": "024696", "event": "HoverExit", "by": "RHand(Direct)", "username": "nishi"}}}, {"node_144": {"label_name": "Object", "node_information": {"name": "Ewe_Word2", "timestamp": "20230829142434", "flame": "024707", "event": "HoverExit", "by": "RHand(Direct)", "username": "nishi"}}}, {"node_145": {"label_name": "Object", "node_information": {"name": "Charcoal_Word7", "timestamp": "20230829142443", "flame": "025389", "event": "HoverEnter", "by": "RHand(Direct)", "username": "nishi"}}}, {"node_146": {"label_name": "Object", "node_information": {"name": "Charcoal_Word7", "timestamp": "20230829142450", "flame": "025849", "event": "SelectExit", "by": "RHand(Direct)", "username": "nishi"}}}, {"node_148": {"label_name": "Object", "node_information": {"name": "Charcoal_Word7", "timestamp": "20230829142450", "flame": "025867", "event": "HoverExit", "by": "RHand(Direct)", "username": "nishi"}}}, {"node_149": {"label_name": "Object", "node_information": {"name": "Charcoal_Word7", "timestamp": "20230829142457", "flame": "026341", "event": "HoverEnter", "by": "LHand(DIrect)", "username": "nishi"}}}, {"node_153": {"label_name": "Object", "node_information": {"name": "Charcoal_Word7", "timestamp": "20230829142502", "flame": "026746", "event": "SelectExit", "by": "LHand(DIrect)", "username": "nishi"}}}, {"node_155": {"label_name": "Object", "node_information": {"name": "Charcoal_Word7", "timestamp": "20230829142503", "flame": "026763", "event": "HoverExit", "by": "LHand(DIrect)", "username": "nishi"}}}, {"node_156": {"label_name": "Object", "node_information": {"name": "Charcoal_Word7", "timestamp": "20230829142513", "flame": "027518", "event": "HoverEnter", "by": "LHand(DIrect)", "username": "nishi"}}}, {"node_157": {"label_name": "Object", "node_information": {"name": "Carving_Word5", "timestamp": "20230829142516", "flame": "027734", "event": "HoverEnter", "by": "RHand(Direct)", "username": "nishi"}}}, {"node_158": {"label_name": "Object", "node_information": {"name": "Carving_Word5", "timestamp": "20230829142516", "flame": "027751", "event": "HoverExit", "by": "RHand(Direct)", "username": "nishi"}}}, {"node_159": {"label_name": "Object", "node_information": {"name": "Ewe_Word2", "timestamp": "20230829142517", "flame": "027800", "event": "HoverEnter", "by": "RHand(Direct)", "username": "nishi"}}}, {"node_160": {"label_name": "Object", "node_information": {"name": "Ewe_Word2", "timestamp": "20230829142517", "flame": "027813", "event": "HoverExit", "by": "RHand(Direct)", "username": "nishi"}}}, {"node_161": {"label_name": "Object", "node_information": {"name": "Charcoal_Word7", "timestamp": "20230829142520", "flame": "028053", "event": "SelectExit", "by": "LHand(DIrect)", "username": "nishi"}}}, {"node_163": {"label_name": "Object", "node_information": {"name": "Charcoal_Word7", "timestamp": "20230829142521", "flame": "028069", "event": "HoverExit", "by": "LHand(DIrect)", "username": "nishi"}}}, {"node_164": {"label_name": "Object", "node_information": {"name": "Carving_Word5", "timestamp": "20230829142532", "flame": "028889", "event": "HoverEnter", "by": "RHand(Direct)", "username": "nishi"}}}, {"node_165": {"label_name": "Object", "node_information": {"name": "Carving_Word5", "timestamp": "20230829142533", "flame": "028948", "event": "SelectExit", "by": "RHand(Direct)", "username": "nishi"}}}, {"node_166": {"label_name": "Object", "node_information": {"name": "Carving_Word5", "timestamp": "20230829142534", "flame": "029003", "event": "HoverExit", "by": "RHand(Direct)", "username": "nishi"}}}, {"node_167": {"label_name": "Object", "node_information": {"name": "Ewe_Word2", "timestamp": "20230829142542", "flame": "029641", "event": "HoverEnter", "by": "RHand(Direct)", "username": "nishi"}}}, {"node_168": {"label_name": "Object", "node_information": {"name": "Ewe_Word2", "timestamp": "20230829142548", "flame": "030008", "event": "SelectExit", "by": "RHand(Direct)", "username": "nishi"}}}, {"node_170": {"label_name": "Object", "node_information": {"name": "Ewe_Word2", "timestamp": "20230829142548", "flame": "030034", "event": "HoverExit", "by": "RHand(Direct)", "username": "nishi"}}}, {"node_171": {"label_name": "Object", "node_information": {"name": "Ewe_Word2", "timestamp": "20230829142550", "flame": "030207", "event": "HoverEnter", "by": "LHand(DIrect)", "username": "nishi"}}}, {"node_172": {"label_name": "Object", "node_information": {"name": "Ewe_Word2", "timestamp": "20230829142550", "flame": "030210", "event": "HoverExit", "by": "LHand(DIrect)", "username": "nishi"}}}, {"node_173": {"label_name": "Object", "node_information": {"name": "Ewe_Word2", "timestamp": "20230829142553", "flame": "030427", "event": "HoverEnter", "by": "RHand(Direct)", "username": "nishi"}}}, {"node_177": {"label_name": "Object", "node_information": {"name": "Ewe_Word2", "timestamp": "20230829142559", "flame": "030820", "event": "SelectExit", "by": "RHand(Direct)", "username": "nishi"}}}, {"node_179": {"label_name": "Object", "node_information": {"name": "Ewe_Word2", "timestamp": "20230829142559", "flame": "030841", "event": "HoverExit", "by": "RHand(Direct)", "username": "nishi"}}}, {"node_180": {"label_name": "Object", "node_information": {"name": "Ewe_Word2", "timestamp": "20230829142559", "flame": "030853", "event": "HoverEnter", "by": "RHand(Direct)", "username": "nishi"}}}, {"node_181": {"label_name": "Object", "node_information": {"name": "Ewe_Word2", "timestamp": "20230829142600", "flame": "030869", "event": "HoverExit", "by": "RHand(Direct)", "username": "nishi"}}}, {"node_182": {"label_name": "Object", "node_information": {"name": "Ewe_Word2", "timestamp": "20230829142610", "flame": "031611", "event": "HoverEnter", "by": "RHand(Direct)", "username": "nishi"}}}, {"node_183": {"label_name": "Object", "node_information": {"name": "Ewe_Word2", "timestamp": "20230829142615", "flame": "031974", "event": "SelectExit", "by": "RHand(Direct)", "username": "nishi"}}}, {"node_185": {"label_name": "Object", "node_information": {"name": "Ewe_Word2", "timestamp": "20230829142616", "flame": "032035", "event": "HoverExit", "by": "RHand(Direct)", "username": "nishi"}}}, {"node_186": {"label_name": "Object", "node_information": {"name": "Ewe_Word2", "timestamp": "20230829142618", "flame": "032179", "event": "HoverEnter", "by": "RHand(Direct)", "username": "nishi"}}}, {"node_192": {"label_name": "Object", "node_information": {"name": "Ewe_Word2", "timestamp": "20230829142619", "flame": "032304", "event": "SelectExit", "by": "RHand(Direct)", "username": "nishi"}}}, {"node_194": {"label_name": "Object", "node_information": {"name": "Ewe_Word2", "timestamp": "20230829142620", "flame": "032336", "event": "HoverEnter", "by": "RHand(Direct)", "username": "nishi"}}}, {"node_195": {"label_name": "Object", "node_information": {"name": "Ewe_Word2", "timestamp": "20230829142620", "flame": "032342", "event": "HoverExit", "by": "RHand(Direct)", "username": "nishi"}}}, {"node_196": {"label_name": "Object", "node_information": {"name": "Ewe_Word2", "timestamp": "20230829142620", "flame": "032378", "event": "HoverEnter", "by": "RHand(Direct)", "username": "nishi"}}}, {"node_197": {"label_name": "Object", "node_information": {"name": "Ewe_Word2", "timestamp": "20230829142621", "flame": "032387", "event": "HoverExit", "by": "RHand(Direct)", "username": "nishi"}}}, {"node_198": {"label_name": "Object", "node_information": {"name": "Ewe_Word2", "timestamp": "20230829142621", "flame": "032402", "event": "HoverEnter", "by": "LHand(DIrect)", "username": "nishi"}}}, {"node_199": {"label_name": "Object", "node_information": {"name": "Ewe_Word2", "timestamp": "20230829142621", "flame": "032410", "event": "HoverExit", "by": "RHand(Direct)", "username": "nishi"}}}, {"node_200": {"label_name": "Object", "node_information": {"name": "Ewe_Word2", "timestamp": "20230829142621", "flame": "032415", "event": "HoverExit", "by": "LHand(DIrect)", "username": "nishi"}}}, {"node_201": {"label_name": "Object", "node_information": {"name": "Ewe_Word2", "timestamp": "20230829142621", "flame": "032426", "event": "HoverEnter", "by": "LHand(DIrect)", "username": "nishi"}}}, {"node_202": {"label_name": "Object", "node_information": {"name": "Ewe_Word2", "timestamp": "20230829142621", "flame": "032429", "event": "HoverEnter", "by": "RHand(Direct)", "username": "nishi"}}}, {"node_203": {"label_name": "Object", "node_information": {"name": "Ewe_Word2", "timestamp": "20230829142621", "flame": "032436", "event": "HoverExit", "by": "LHand(DIrect)", "username": "nishi"}}}, {"node_204": {"label_name": "Object", "node_information": {"name": "Ewe_Word2", "timestamp": "20230829142621", "flame": "032436", "event": "HoverEnter", "by": "RHand(Direct)", "username": "nishi"}}}, {"node_205": {"label_name": "Object", "node_information": {"name": "Ewe_Word2", "timestamp": "20230829142621", "flame": "032437", "event": "HoverExit", "by": "RHand(Direct)", "username": "nishi"}}}, {"node_206": {"label_name": "Object", "node_information": {"name": "Ewe_Word2", "timestamp": "20230829142621", "flame": "032448", "event": "HoverExit", "by": "RHand(Direct)", "username": "nishi"}}}, {"node_207": {"label_name": "Object", "node_information": {"name": "Ewe_Word2", "timestamp": "20230829142623", "flame": "032580", "event": "HoverEnter", "by": "RHand(Direct)", "username": "nishi"}}}, {"node_213": {"label_name": "Object", "node_information": {"name": "Ewe_Word2", "timestamp": "20230829142625", "flame": "032712", "event": "SelectExit", "by": "RHand(Direct)", "username": "nishi"}}}, {"node_215": {"label_name": "Object", "node_information": {"name": "Ewe_Word2", "timestamp": "20230829142626", "flame": "032763", "event": "HoverExit", "by": "RHand(Direct)", "username": "nishi"}}}, {"node_216": {"label_name": "Object", "node_information": {"name": "Ewe_Word2", "timestamp": "20230829142627", "flame": "032874", "event": "HoverEnter", "by": "RHand(Direct)", "username": "nishi"}}}, {"node_223": {"label_name": "Object", "node_information": {"name": "Ewe_Word2", "timestamp": "20230829142630", "flame": "033099", "event": "SelectExit", "by": "RHand(Direct)", "username": "nishi"}}}, {"node_227": {"label_name": "Object", "node_information": {"name": "Ewe_Word2", "timestamp": "20230829142631", "flame": "033133", "event": "HoverExit", "by": "RHand(Direct)", "username": "nishi"}}}, {"node_228": {"label_name": "Object", "node_information": {"name": "Ewe_Word2", "timestamp": "20230829142631", "flame": "033149", "event": "HoverEnter", "by": "RHand(Direct)", "username": "nishi"}}}, {"node_229": {"label_name": "Object", "node_information": {"name": "Ewe_Word2", "timestamp": "20230829142631", "flame": "033164", "event": "HoverExit", "by": "RHand(Direct)", "username": "nishi"}}}, {"node_230": {"label_name": "Object", "node_information": {"name": "Chick_Word3", "timestamp": "20230829142642", "flame": "033924", "event": "HoverEnter", "by": "RHand(Direct)", "username": "nishi"}}}, {"node_234": {"label_name": "Object", "node_information": {"name": "Chick_Word3", "timestamp": "20230829142647", "flame": "034310", "event": "SelectExit", "by": "RHand(Direct)", "username": "nishi"}}}, {"node_238": {"label_name": "Object", "node_information": {"name": "Chick_Word3", "timestamp": "20230829142648", "flame": "034378", "event": "HoverExit", "by": "RHand(Direct)", "username": "nishi"}}}, {"node_239": {"label_name": "Object", "node_information": {"name": "Chick_Word3", "timestamp": "20230829142652", "flame": "034663", "event": "HoverEnter", "by": "RHand(Direct)", "username": "nishi"}}}, {"node_241": {"label_name": "Object", "node_information": {"name": "Chick_Word3", "timestamp": "20230829142658", "flame": "035093", "event": "SelectExit", "by": "RHand(Direct)", "username": "nishi"}}}, {"node_244": {"label_name": "Object", "node_information": {"name": "Chick_Word3", "timestamp": "20230829142659", "flame": "035148", "event": "HoverExit", "by": "RHand(Direct)", "username": "nishi"}}}, {"node_245": {"label_name": "Object", "node_information": {"name": "Chick_Word3", "timestamp": "20230829142703", "flame": "035452", "event": "HoverEnter", "by": "RHand(Direct)", "username": "nishi"}}}, {"node_247": {"label_name": "Object", "node_information": {"name": "Chick_Word3", "timestamp": "20230829142707", "flame": "035729", "event": "SelectExit", "by": "RHand(Direct)", "username": "nishi"}}}, {"node_250": {"label_name": "Object", "node_information": {"name": "Chick_Word3", "timestamp": "20230829142709", "flame": "035868", "event": "HoverExit", "by": "LHand(DIrect)", "username": "nishi"}}}, {"node_251": {"label_name": "Object", "node_information": {"name": "Chick_Word3", "timestamp": "20230829142710", "flame": "035953", "event": "HoverEnter", "by": "RHand(Direct)", "username": "nishi"}}}, {"node_253": {"label_name": "Object", "node_information": {"name": "Chick_Word3", "timestamp": "20230829142712", "flame": "036073", "event": "SelectExit", "by": "RHand(Direct)", "username": "nishi"}}}, {"node_256": {"label_name": "Object", "node_information": {"name": "Chick_Word3", "timestamp": "20230829142713", "flame": "036148", "event": "HoverExit", "by": "RHand(Direct)", "username": "nishi"}}}, {"node_257": {"label_name": "Object", "node_information": {"name": "Chick_Word3", "timestamp": "20230829142719", "flame": "036595", "event": "HoverEnter", "by": "RHand(Direct)", "username": "nishi"}}}, {"node_270": {"label_name": "Object", "node_information": {"name": "Chick_Word3", "timestamp": "20230829142727", "flame": "037192", "event": "SelectExit", "by": "RHand(Direct)", "username": "nishi"}}}, {"node_271": {"label_name": "Object", "node_information": {"name": "Chick_Word3", "timestamp": "20230829142728", "flame": "037252", "event": "HoverExit", "by": "RHand(Direct)", "username": "nishi"}}}, {"node_272": {"label_name": "Object", "node_information": {"name": "Chick_Word3", "timestamp": "20230829142729", "flame": "037324", "event": "HoverEnter", "by": "LHand(DIrect)", "username": "nishi"}}}, {"node_273": {"label_name": "Object", "node_information": {"name": "Chick_Word3", "timestamp": "20230829142731", "flame": "037468", "event": "HoverExit", "by": "LHand(DIrect)", "username": "nishi"}}}, {"node_274": {"label_name": "Object", "node_information": {"name": "Chick_Word3", "timestamp": "20230829142733", "flame": "037589", "event": "HoverEnter", "by": "LHand(DIrect)", "username": "nishi"}}}, {"node_275": {"label_name": "Object", "node_information": {"name": "Chick_Word3", "timestamp": "20230829142734", "flame": "037681", "event": "HoverExit", "by": "LHand(DIrect)", "username": "nishi"}}}, {"node_276": {"label_name": "Object", "node_information": {"name": "Garland_Word6", "timestamp": "20230829142744", "flame": "038417", "event": "HoverEnter", "by": "RHand(Direct)", "username": "nishi"}}}, {"node_277": {"label_name": "Object", "node_information": {"name": "Garland_Word6", "timestamp": "20230829142752", "flame": "038968", "event": "SelectExit", "by": "RHand(Direct)", "username": "nishi"}}}, {"node_278": {"label_name": "Object", "node_information": {"name": "Garland_Word6", "timestamp": "20230829142752", "flame": "038968", "event": "HoverEnter", "by": "RHand(Direct)", "username": "nishi"}}}, {"node_280": {"label_name": "Object", "node_information": {"name": "Garland_Word6", "timestamp": "20230829142753", "flame": "039044", "event": "HoverExit", "by": "RHand(Direct)", "username": "nishi"}}}, {"node_281": {"label_name": "Object", "node_information": {"name": "Garland_Word6", "timestamp": "20230829142753", "flame": "039044", "event": "HoverExit", "by": "RHand(Direct)", "username": "nishi"}}}, {"node_282": {"label_name": "Object", "node_information": {"name": "Garland_Word6", "timestamp": "20230829142754", "flame": "039133", "event": "HoverEnter", "by": "RHand(Direct)", "username": "nishi"}}}, {"node_283": {"label_name": "Object", "node_information": {"name": "Garland_Word6", "timestamp": "20230829142810", "flame": "040302", "event": "SelectExit", "by": "RHand(Direct)", "username": "nishi"}}}, {"node_284": {"label_name": "Object", "node_information": {"name": "Garland_Word6", "timestamp": "20230829142810", "flame": "040302", "event": "HoverEnter", "by": "RHand(Direct)", "username": "nishi"}}}, {"node_285": {"label_name": "Object", "node_information": {"name": "Garland_Word6", "timestamp": "20230829142810", "flame": "040302", "event": "HoverEnter", "by": "RHand(Direct)", "username": "nishi"}}}, {"node_287": {"label_name": "Object", "node_information": {"name": "Garland_Word6", "timestamp": "20230829142812", "flame": "040427", "event": "HoverExit", "by": "RHand(Direct)", "username": "nishi"}}}, {"node_288": {"label_name": "Object", "node_information": {"name": "Garland_Word6", "timestamp": "20230829142812", "flame": "040428", "event": "HoverExit", "by": "RHand(Direct)", "username": "nishi"}}}, {"node_289": {"label_name": "Object", "node_information": {"name": "Garland_Word6", "timestamp": "20230829142812", "flame": "040430", "event": "HoverExit", "by": "RHand(Direct)", "username": "nishi"}}}, {"node_290": {"label_name": "Object", "node_information": {"name": "Garland_Word6", "timestamp": "20230829142813", "flame": "040461", "event": "HoverEnter", "by": "RHand(Direct)", "username": "nishi"}}}, {"node_291": {"label_name": "Object", "node_information": {"name": "Garland_Word6", "timestamp": "20230829142813", "flame": "040466", "event": "HoverExit", "by": "RHand(Direct)", "username": "nishi"}}}, {"node_292": {"label_name": "Object", "node_information": {"name": "Garland_Word6", "timestamp": "20230829142814", "flame": "040531", "event": "HoverEnter", "by": "RHand(Direct)", "username": "nishi"}}}, {"node_293": {"label_name": "Object", "node_information": {"name": "Garland_Word6", "timestamp": "20230829142814", "flame": "040542", "event": "HoverExit", "by": "RHand(Direct)", "username": "nishi"}}}, {"node_298": {"label_name": "Object", "node_information": {"name": "Granite_Word4", "timestamp": "20230829142844", "flame": "042703", "event": "HoverEnter", "by": "RHand(Direct)", "username": "nishi"}}}, {"node_344": {"label_name": "Object", "node_information": {"name": "Granite_Word4", "timestamp": "20230829142851", "flame": "043246", "event": "SelectExit", "by": "RHand(Direct)", "username": "nishi"}}}, {"node_348": {"label_name": "Object", "node_information": {"name": "Granite_Word4", "timestamp": "20230829142851", "flame": "043250", "event": "HoverEnter", "by": "RHand(Direct)", "username": "nishi"}}}, {"node_349": {"label_name": "Object", "node_information": {"name": "Granite_Word4", "timestamp": "20230829142852", "flame": "043280", "event": "HoverExit", "by": "RHand(Direct)", "username": "nishi"}}}, {"node_356": {"label_name": "Object", "node_information": {"name": "Granite_Word4", "timestamp": "20230829142853", "flame": "043357", "event": "HoverEnter", "by": "RHand(Direct)", "username": "nishi"}}}, {"node_357": {"label_name": "Object", "node_information": {"name": "Granite_Word4", "timestamp": "20230829142853", "flame": "043386", "event": "HoverExit", "by": "RHand(Direct)", "username": "nishi"}}}, {"node_358": {"label_name": "Object", "node_information": {"name": "Granite_Word4", "timestamp": "20230829142853", "flame": "043387", "event": "HoverExit", "by": "RHand(Direct)", "username": "nishi"}}}, {"node_359": {"label_name": "Object", "node_information": {"name": "Granite_Word4", "timestamp": "20230829142857", "flame": "043698", "event": "HoverEnter", "by": "RHand(Direct)", "username": "nishi"}}}, {"node_363": {"label_name": "Object", "node_information": {"name": "Granite_Word4", "timestamp": "20230829142905", "flame": "044222", "event": "SelectExit", "by": "RHand(Direct)", "username": "nishi"}}}, {"node_430": {"label_name": "Object", "node_information": {"name": "Granite_Word4", "timestamp": "20230829142906", "flame": "044296", "event": "HoverEnter", "by": "RHand(Direct)", "username": "nishi"}}}, {"node_431": {"label_name": "Object", "node_information": {"name": "Granite_Word4", "timestamp": "20230829142906", "flame": "044315", "event": "HoverExit", "by": "RHand(Direct)", "username": "nishi"}}}, {"node_432": {"label_name": "Object", "node_information": {"name": "Granite_Word4", "timestamp": "20230829142906", "flame": "044321", "event": "HoverExit", "by": "RHand(Direct)", "username": "nishi"}}}, {"node_433": {"label_name": "Object", "node_information": {"name": "Granite_Word4", "timestamp": "20230829142915", "flame": "044953", "event": "HoverEnter", "by": "RHand(Direct)", "username": "nishi"}}}, {"node_434": {"label_name": "Object", "node_information": {"name": "Granite_Word4", "timestamp": "20230829142917", "flame": "045137", "event": "HoverExit", "by": "RHand(Direct)", "username": "nishi"}}}, {"node_435": {"label_name": "Object", "node_information": {"name": "Granite_Word4", "timestamp": "20230829142918", "flame": "045182", "event": "HoverEnter", "by": "LHand(DIrect)", "username": "nishi"}}}, {"node_436": {"label_name": "Object", "node_information": {"name": "Granite_Word4", "timestamp": "20230829142918", "flame": "045196", "event": "HoverEnter", "by": "LHand(DIrect)", "username": "nishi"}}}, {"node_437": {"label_name": "Object", "node_information": {"name": "Granite_Word4", "timestamp": "20230829142919", "flame": "045219", "event": "HoverExit", "by": "LHand(DIrect)", "username": "nishi"}}}, {"node_438": {"label_name": "Object", "node_information": {"name": "Granite_Word4", "timestamp": "20230829142919", "flame": "045234", "event": "HoverExit", "by": "LHand(DIrect)", "username": "nishi"}}}, {"node_439": {"label_name": "Object", "node_information": {"name": "Chick_Word3", "timestamp": "20230829142925", "flame": "045716", "event": "HoverEnter", "by": "RHand(Direct)", "username": "nishi"}}}, {"node_721": {"label_name": "Object", "node_information": {"name": "Chick_Word3", "timestamp": "20230829142930", "flame": "046060", "event": "SelectExit", "by": "RHand(Direct)", "username": "nishi"}}}, {"node_722": {"label_name": "Object", "node_information": {"name": "Granite_Word4", "timestamp": "20230829142930", "flame": "046060", "event": "HoverEnter", "by": "RHand(Direct)", "username": "nishi"}}}, {"node_811": {"label_name": "Object", "node_information": {"name": "Granite_Word4", "timestamp": "20230829142932", "flame": "046154", "event": "HoverExit", "by": "RHand(Direct)", "username": "nishi"}}}, {"node_813": {"label_name": "Object", "node_information": {"name": "Chick_Word3", "timestamp": "20230829142932", "flame": "046157", "event": "HoverExit", "by": "LHand(DIrect)", "username": "nishi"}}}, {"node_816": {"label_name": "Object", "node_information": {"name": "Granite_Word4", "timestamp": "20230829142932", "flame": "046199", "event": "HoverEnter", "by": "RHand(Direct)", "username": "nishi"}}}, {"node_817": {"label_name": "Object", "node_information": {"name": "Granite_Word4", "timestamp": "20230829142932", "flame": "046208", "event": "HoverExit", "by": "RHand(Direct)", "username": "nishi"}}}, {"node_818": {"label_name": "Object", "node_information": {"name": "Granite_Word4", "timestamp": "20230829142933", "flame": "046277", "event": "HoverEnter", "by": "RHand(Direct)", "username": "nishi"}}}, {"node_826": {"label_name": "Object", "node_information": {"name": "Granite_Word4", "timestamp": "20230829142934", "flame": "046333", "event": "SelectExit", "by": "RHand(Direct)", "username": "nishi"}}}, {"node_827": {"label_name": "Object", "node_information": {"name": "Granite_Word4", "timestamp": "20230829142934", "flame": "046333", "event": "HoverExit", "by": "RHand(Direct)", "username": "nishi"}}}, {"node_830": {"label_name": "Object", "node_information": {"name": "Ewe_Word2", "timestamp": "20230829142954", "flame": "047744", "event": "HoverEnter", "by": "RHand(Direct)", "username": "nishi"}}}, {"node_831": {"label_name": "Object", "node_information": {"name": "Ewe_Word2", "timestamp": "20230829142955", "flame": "047845", "event": "HoverExit", "by": "RHand(Direct)", "username": "nishi"}}}, {"node_832": {"label_name": "Object", "node_information": {"name": "Carving_Word5", "timestamp": "20230829143031", "flame": "050434", "event": "HoverEnter", "by": "RHand(Direct)", "username": "nishi"}}}]